vending_machine.v
// Code your design here
module vending_machine(
  input wire i_nickle,i_dime, i_quarter,
  input wire i_clk,
  output reg [2:0] o_change,
  output reg o_soda
);
  localparam S0 =2'b00, S1 = 2'b01, S2= 2'b10, S3= 2'b11;
  reg [1:0] current_state, next_state;
  reg next_soda;
  reg [2:0] next_change;
  
  always @(posedge i_clk) begin
    current_state <= next_state;
    o_soda <= next_soda ;
    o_change <= next_change;
  end
  
  always @(*) begin
    next_soda = 1'b0;
    next_change = 3'b000;
    
    case (current_state) 
      S0: case ({i_quarter,i_dime,i_nickle})
        3'b100: begin
          next_state = S0;
          next_soda = 1'b1;
          next_change = 3'b001;
        end
        3'b010: begin
          next_state = S2;
          next_soda =1'b0;
          next_change = 3'b000;
        end
        3'b001: begin
          next_state = S1;
          next_soda =1'b0;
          next_change = 3'b000;
        end
        default: next_state = S0;
      endcase
      
      S1: case ({i_quarter,i_dime,i_nickle})
        3'b100: begin
          next_state = S0;
          next_soda = 1'b1;
          next_change = 3'b010;
        end
        3'b010: begin
          next_state = S3;
          next_soda =1'b0;
          next_change = 3'b000;
        end
        3'b001: begin
          next_state = S2;
          next_soda =1'b0;
          next_change = 3'b000;
        end
        default: next_state = S1;
      endcase
        
      S2: case ({i_quarter,i_dime,i_nickle})
        3'b100: begin
          next_state = S0;
          next_soda = 1'b1;
          next_change = 3'b011;
        end
        3'b010: begin
          next_state = S0;
          next_soda =1'b1;
          next_change = 3'b000;
        end
        3'b001: begin
          next_state = S3;
          next_soda =1'b0;
          next_change = 3'b000;
        end
        default: next_state = S2;
      endcase
      
      S3: case ({i_quarter,i_dime,i_nickle})
        3'b100: begin
          next_state = S0;
          next_soda = 1'b1;
          next_change = 3'b100;
        end
        3'b010: begin
          next_state = S0;
          next_soda =1'b1;
          next_change = 3'b001;
        end
        3'b001: begin
          next_state = S0;
          next_soda =1'b1;
          next_change = 3'b000;
        end
        default: next_state = S3;
      endcase
      default : begin 
        next_state <= S0;
        next_soda <= 1'b0;
        next_change <= 3'b000;
      end
      
    endcase
  end
  
endmodule

tb_vending_machine.v
// Code your testbench here
// or browse Examples

module tb_vending_machine;
  reg i_clk;
  reg i_nickle, i_dime, i_quarter;
  wire o_soda;
  wire [2:0] o_change;
  
  vending_machine dut(
    .i_clk(i_clk),
    .i_nickle(i_nickle),
    .i_dime(i_dime),
    .i_quarter(i_quarter),
    .o_soda(o_soda),
    .o_change(o_change)
  );
  
  initial begin
    i_clk =0 ;
    forever #5 i_clk = ~i_clk;
  end
  
  initial begin
    
    #5 i_nickle = 0;
       i_dime = 0;
       i_quarter = 0;

    // Apply test vectors
    // Apply first Nickel (5¢)
    #10 i_dime = 1; 
    #10 i_dime = 0;

    // Apply second Dime (10¢)
    #10 i_quarter = 1; 
    #10 i_quarter = 0;

    // Apply Quarter (25¢)
    #10 i_nickle = 1;
    #10 i_nickle = 0;
    	i_dime =1;
    #10 i_dime = 0;
    	i_quarter =1;
    #10 i_quarter = 0;

   

    // Finish simulation after sufficient time
    #100;
    $finish;
  end
endmodule

vending_machine_waveform.vcd
$date
	Sun Oct 05 00:04:06 2025
$end
$version
	QuestaSim Version 10.2c
$end
$timescale
	1ns
$end

$scope module tb_vending_machine $end
$var reg 1 ! i_clk $end
$var reg 1 " i_nickle $end
$var reg 1 # i_dime $end
$var reg 1 $ i_quarter $end
$var wire 1 % o_soda $end
$var wire 1 & o_change [2] $end
$var wire 1 ' o_change [1] $end
$var wire 1 ( o_change [0] $end

$scope module dut $end
$var parameter 2 ) S0 $end
$var parameter 2 * S1 $end
$var parameter 2 + S2 $end
$var parameter 2 , S3 $end
$var wire 1 - i_nickle $end
$var wire 1 . i_dime $end
$var wire 1 / i_quarter $end
$var wire 1 0 i_clk $end
$var reg 3 1 o_change [2:0] $end
$var reg 1 2 o_soda $end
$var reg 2 3 current_state [1:0] $end
$var reg 2 4 next_state [1:0] $end
$var reg 1 5 next_soda $end
$var reg 3 6 next_change [2:0] $end
$upscope $end
$upscope $end
$enddefinitions $end
#0
$dumpvars
0!
0"
0#
0$
bx 1
x2
bx 3
b0 4
05
b0 6
b0 )
b1 *
b10 +
b11 ,
x%
x(
x'
x&
0/
0.
0-
00
$end
#5
1!
1"
10
1-
b0 3
02
b0 1
0%
0(
0'
0&
b1 4
#10
0!
00
#15
0"
1!
0-
10
b0 4
b1 3
b1 4
#20
0!
00
#25
1#
1!
1.
10
b11 4
#30
0!
00
#35
0#
1!
0.
10
b1 4
b11 3
b11 4
#40
0!
00
#45
1$
1!
1/
10
b0 4
15
b100 6
#50
0!
00
#55
0$
1!
0/
10
05
b0 6
b11 4
b0 3
12
b100 1
1%
1&
b0 4
#60
0!
00
#65
1!
10
02
b0 1
0%
0&
#70
0!
00
#75
1#
1!
1.
10
b10 4
#80
0!
00
#85
0#
1!
0.
10
b0 4
b10 3
b10 4
#90
0!
00
#95
1$
1!
1/
10
b0 4
15
b11 6
#100
0!
00
#105
0$
1!
0/
10
05
b0 6
b10 4
b0 3
12
b11 1
1%
1(
1'
b0 4
#110
0!
00
#115
1!
10
02
b0 1
0%
0(
0'
